ground_control/__init__.py
ground_control/__main__.py
ground_control/app.py
ground_control/main.py
ground_control/cli/__init__.py
ground_control/cli/process_list.py
ground_control/utils/__init__.py
ground_control/utils/formatting.py
ground_control/utils/system_metrics.py
ground_control/widgets/__init__.py
ground_control/widgets/base.py
ground_control/widgets/cpu.py
ground_control/widgets/disk.py
ground_control/widgets/gpu.py
ground_control/widgets/memory.py
ground_control/widgets/network.py
ground_control/widgets/temperature.py
ground_control_tui-1.2.3.dist-info/licenses/LICENSE
ground_control_tui-1.2.3.dist-info/METADATA
ground_control_tui-1.2.3.dist-info/WHEEL
ground_control_tui-1.2.3.dist-info/entry_points.txt
ground_control_tui-1.2.3.dist-info/top_level.txt
ground_control_tui-1.2.3.dist-info/RECORD
