Metadata-Version: 2.4
Name: ground-control-tui
Version: 1.2.3
Summary: A Python Textual app for monitoring hardware in the terminal
Author-email: Alberto Rota <alberto1.rota@polimi.it>
Project-URL: Homepage, https://github.com/alberto-rota/ground-control
Classifier: Programming Language :: Python :: 3
Classifier: Operating System :: OS Independent
License-File: LICENSE
Requires-Dist: click==8.1.8
Requires-Dist: linkify-it-py==2.0.3
Requires-Dist: markdown-it-py==3.0.0
Requires-Dist: mdit-py-plugins==0.4.2
Requires-Dist: mdurl==0.1.2
Requires-Dist: numpy>=1.24.4
Requires-Dist: nvidia-ml-py==13.580.82
Requires-Dist: nvitop==1.6.1
Requires-Dist: platformdirs==4.3.6
Requires-Dist: plotext==5.3.2
Requires-Dist: psutil==7.2.1
Requires-Dist: pygments==2.19.2
Requires-Dist: rich==14.2.0
Requires-Dist: textual==6.2.1
Requires-Dist: textualize==0.1
Requires-Dist: typing-extensions==4.13.2
Requires-Dist: uc-micro-py==1.0.3
Dynamic: license-file
